partiallabelmonitor/__init__.py
partiallabelmonitor/data/__init__.py
partiallabelmonitor/data/_databatcher.py
PartialLabelMonitor-0.0.0.dist-info/LICENSE
PartialLabelMonitor-0.0.0.dist-info/METADATA
PartialLabelMonitor-0.0.0.dist-info/WHEEL
PartialLabelMonitor-0.0.0.dist-info/top_level.txt
PartialLabelMonitor-0.0.0.dist-info/RECORD
